{
  "version": 1,
  "docsBaseUrl": "https://livon.tech",
  "generatedNotice": "<!-- Generated from website/docs/packages/*.md. Do not edit directly. -->",
  "targets": [
    {
      "id": "@livon/runtime",
      "source": "website/docs/packages/runtime.md",
      "target": "packages/runtime/README.md"
    },
    {
      "id": "@livon/schema",
      "source": "website/docs/packages/schema.md",
      "target": "packages/schema/README.md"
    },
    {
      "id": "@livon/client",
      "source": "website/docs/packages/client.md",
      "target": "packages/client/README.md"
    },
    {
      "id": "@livon/client-ws-transport",
      "source": "website/docs/packages/client-ws-transport.md",
      "target": "packages/client-ws-transport/README.md"
    },
    {
      "id": "@livon/node-ws-transport",
      "source": "website/docs/packages/node-ws-transport.md",
      "target": "packages/server-ws-transport/README.md"
    },
    {
      "id": "@livon/dlq-module",
      "source": "website/docs/packages/dlq-module.md",
      "target": "packages/dlq-module/README.md"
    },
    {
      "id": "@livon/cli",
      "source": "website/docs/packages/cli.md",
      "target": "packages/cli/README.md"
    },
    {
      "id": "@livon/sync",
      "source": "website/docs/packages/sync.md",
      "target": "packages/sync/README.md"
    },
    {
      "id": "@livon/react",
      "source": "website/docs/packages/react.md",
      "target": "packages/react/README.md"
    },
    {
      "id": "root-readme",
      "source": "website/docs/index.md",
      "target": "README.md",
      "generatedNotice": "<!-- Generated from website/docs/index.md. Do not edit directly. -->"
    },
    {
      "id": "root-contributing",
      "source": "website/docs/core/contributing.md",
      "target": "CONTRIBUTING.md",
      "generatedNotice": "<!-- Generated from website/docs/core/contributing.md. Do not edit directly. -->"
    },
    {
      "id": "root-governance",
      "source": "website/docs/core/governance.md",
      "target": "GOVERNANCE.md",
      "generatedNotice": "<!-- Generated from website/docs/core/governance.md. Do not edit directly. -->"
    },
    {
      "id": "root-code-of-conduct",
      "source": "website/docs/core/code-of-conduct.md",
      "target": "CODE_OF_CONDUCT.md",
      "generatedNotice": "<!-- Generated from website/docs/core/code-of-conduct.md. Do not edit directly. -->"
    },
    {
      "id": "root-support",
      "source": "website/docs/core/support.md",
      "target": "SUPPORT.md",
      "generatedNotice": "<!-- Generated from website/docs/core/support.md. Do not edit directly. -->"
    },
    {
      "id": "root-security",
      "source": "website/docs/core/security.md",
      "target": "SECURITY.md",
      "generatedNotice": "<!-- Generated from website/docs/core/security.md. Do not edit directly. -->"
    },
    {
      "id": "github-security",
      "source": "website/docs/core/security.md",
      "target": ".github/SECURITY.md",
      "generatedNotice": "<!-- Generated from website/docs/core/security.md. Do not edit directly. -->"
    },
    {
      "id": "root-changelog",
      "source": "website/docs/core/release-notes.md",
      "target": "CHANGELOG.md",
      "generatedNotice": "<!-- Generated from website/docs/core/release-notes.md. Do not edit directly. -->"
    },
    {
      "id": "root-best-practices",
      "source": "website/docs/core/openssf-best-practices.md",
      "target": "BEST_PRACTICES.md",
      "generatedNotice": "<!-- Generated from website/docs/core/openssf-best-practices.md. Do not edit directly. -->"
    }
  ]
}
